{
  "$schema": "https://developer.microsoft.com/json-schemas/core-build/serve.schema.json",
  "port": 4321,
  "https": true,
  "serveConfigurations": {
    "default": {
      "pageUrl": "https://shaysilber2.sharepoint.com/sites/demo/SitePages/home.aspx",
      "customActions": {
        "4320b0e2-8a6c-4bba-be2e-382dc60a5c12": {
          "location": "ClientSideExtension.ApplicationCustomizer",
          "properties": {
            "testMessage": "Test message",
            "Top":"Some Data"
          }
        }
      }
    },
    "searchHeader": {
      "pageUrl": "https://shaysilber2.sharepoint.com/sites/demo/SitePages/home.aspx",
      "customActions": {
        "4320b0e2-8a6c-4bba-be2e-382dc60a5c12": {
          "location": "ClientSideExtension.ApplicationCustomizer",
          "properties": {
            "testMessage": "Test message",
            "Top":"Some Data"
          }
        }
      }
    }
  }
}
